postfoam/__init__.py
postfoam/foamtopy.py
postfoam/script.py
postfoam/test.py
postfoam-0.1.1.dist-info/LICENSE
postfoam-0.1.1.dist-info/METADATA
postfoam-0.1.1.dist-info/WHEEL
postfoam-0.1.1.dist-info/top_level.txt
postfoam-0.1.1.dist-info/RECORD
