Metadata-Version: 2.1
Name: postfoam
Version: 0.1.1
Summary: A python library for postporcessing openfoam simulations.
Author: Ioannis Kyritsopoulos
Author-email: yiagoskyrits@gmail.com
License: MIT
Keywords: OpenFOAM,postprocessing
Classifier: Development Status :: 5 - Production/Stable
Classifier: Intended Audience :: Science/Research
Classifier: License :: OSI Approved :: MIT License
Classifier: Operating System :: POSIX :: Linux
Classifier: Programming Language :: Python :: 3
Classifier: Topic :: Scientific/Engineering
License-File: LICENSE
Requires-Dist: numpy
Requires-Dist: matplotlib
Requires-Dist: scipy
Requires-Dist: re
